academicmarkdown/HTMLFilter.py
academicmarkdown/MDFilter.py
academicmarkdown/_BaseParser.py
academicmarkdown/_CodeParser.py
academicmarkdown/_ConstantParser.py
academicmarkdown/_ExecParser.py
academicmarkdown/_FigureParser.py
academicmarkdown/_IncludeParser.py
academicmarkdown/_ODTFixer.py
academicmarkdown/_Pandoc.py
academicmarkdown/_PythonParser.py
academicmarkdown/_TOCParser.py
academicmarkdown/_TableParser.py
academicmarkdown/_VideoParser.py
academicmarkdown/_WcParser.py
academicmarkdown/_WkHtmlToPdf.py
academicmarkdown/_YAMLParser.py
academicmarkdown/_ZoteroParser.py
academicmarkdown/__init__.py
academicmarkdown/build.py
academicmarkdown/constants.py
academicmarkdown/git.py
academicmarkdown/py3compat.py
academicmarkdown/test.py
academicmarkdown/tools.py
python_academicmarkdown-0.9.0.dist-info/DESCRIPTION.rst
python_academicmarkdown-0.9.0.dist-info/METADATA
python_academicmarkdown-0.9.0.dist-info/RECORD
python_academicmarkdown-0.9.0.dist-info/WHEEL
python_academicmarkdown-0.9.0.dist-info/metadata.json
python_academicmarkdown-0.9.0.dist-info/top_level.txt
